pkg/__init__.py
pkg/blume_injector.py
pkg/injector.py
input_llm-0.1.0.dist-info/LICENSE
input_llm-0.1.0.dist-info/METADATA
input_llm-0.1.0.dist-info/WHEEL
input_llm-0.1.0.dist-info/top_level.txt
input_llm-0.1.0.dist-info/RECORD
