Metadata-Version: 2.1
Name: input-llm
Version: 0.1.0
Summary: Intercept OpenAI inputs
Author: Ethan Hou
Author-email: ethanfhou10@gmail.com
Classifier: Programming Language :: Python :: 3
Classifier: License :: OSI Approved :: MIT License
Classifier: Operating System :: OS Independent
License-File: LICENSE
